odoo/addons/energy_communities/README.md
odoo/addons/energy_communities/__init__.py
odoo/addons/energy_communities/__manifest__.py
odoo/addons/energy_communities/config.py
odoo/addons/energy_communities/hooks.py
odoo/addons/energy_communities/utils.py
odoo/addons/energy_communities/client_map/__init__.py
odoo/addons/energy_communities/client_map/config.py
odoo/addons/energy_communities/client_map/resources/__init__.py
odoo/addons/energy_communities/client_map/resources/landing_cmplace.py
odoo/addons/energy_communities/components/__init__.py
odoo/addons/energy_communities/components/account_utils.py
odoo/addons/energy_communities/components/collections.py
odoo/addons/energy_communities/components/contract_utils.py
odoo/addons/energy_communities/components/product_utils.py
odoo/addons/energy_communities/components/sale_order_utils.py
odoo/addons/energy_communities/components/user_creator.py
odoo/addons/energy_communities/components/user_role_utils.py
odoo/addons/energy_communities/controllers/__init__.py
odoo/addons/energy_communities/controllers/_controllers.py
odoo/addons/energy_communities/controllers/website_form_controllers.py
odoo/addons/energy_communities/data/auth_oauth_provider_data.xml
odoo/addons/energy_communities/data/community_maps_data.xml
odoo/addons/energy_communities/data/energy_action.xml
odoo/addons/energy_communities/data/ir_cron.xml
odoo/addons/energy_communities/data/mail_template_data.xml
odoo/addons/energy_communities/data/mail_templates_email_layouts.xml
odoo/addons/energy_communities/data/product_data.xml
odoo/addons/energy_communities/data/utm_data.xml
odoo/addons/energy_communities/demo/api_key_demo.xml
odoo/addons/energy_communities/demo/cm_maps_demo.xml
odoo/addons/energy_communities/demo/landing_page_demo.xml
odoo/addons/energy_communities/demo/res_company_demo.xml
odoo/addons/energy_communities/demo/res_lang_demo.xml
odoo/addons/energy_communities/demo/res_user_demo.xml
odoo/addons/energy_communities/i18n/ca_ES.po
odoo_addon_energy_communities-16.0.0.7.7.dist-info/METADATA
odoo_addon_energy_communities-16.0.0.7.7.dist-info/WHEEL
odoo_addon_energy_communities-16.0.0.7.7.dist-info/top_level.txt
odoo_addon_energy_communities-16.0.0.7.7.dist-info/RECORD
