Metadata-Version: 2.1
Name: odoo-addon-energy_communities
Version: 16.0.0.7.7
Requires-Python: >=3.10
Requires-Dist: Faker==38.0.0
Requires-Dist: odoo-addon-account_banking_mandate>=16.0dev,<16.1dev
Requires-Dist: odoo-addon-account_lock_date_update>=16.0dev,<16.1dev
Requires-Dist: odoo-addon-account_multicompany_easy_creation>=16.0dev,<16.1dev
Requires-Dist: odoo-addon-account_payment_order>=16.0dev,<16.1dev
Requires-Dist: odoo-addon-account_reconcile_oca>=16.0dev,<16.1dev
Requires-Dist: odoo-addon-auth_api_key>=16.0dev,<16.1dev
Requires-Dist: odoo-addon-auth_oidc>=16.0dev,<16.1dev
Requires-Dist: odoo-addon-base_rest>=16.0dev,<16.1dev
Requires-Dist: odoo-addon-base_technical_features>=16.0dev,<16.1dev
Requires-Dist: odoo-addon-base_user_role>=16.0dev,<16.1dev
Requires-Dist: odoo-addon-base_user_role_company>=16.0dev,<16.1dev
Requires-Dist: odoo-addon-community_maps>=16.0dev,<16.1dev
Requires-Dist: odoo-addon-community_maps_key_submissions>=16.0dev,<16.1dev
Requires-Dist: odoo-addon-l10n_es_aeat>=16.0dev,<16.1dev
Requires-Dist: odoo-addon-l10n_es_aeat_sii_oca>=16.0dev,<16.1dev
Requires-Dist: odoo-addon-mail_multicompany>=16.0dev,<16.1dev
Requires-Dist: odoo-addon-mail_template_multi_company>=16.0dev,<16.1dev
Requires-Dist: odoo-addon-metadata>=16.0dev,<16.1dev
Requires-Dist: odoo-addon-partner_firstname>=16.0dev,<16.1dev
Requires-Dist: odoo-addon-partner_multi_company>=16.0dev,<16.1dev
Requires-Dist: odoo-addon-queue_job>=16.0dev,<16.1dev
Requires-Dist: odoo-test-helper==2.1.1
Requires-Dist: odoo>=16.0a,<16.1dev
Requires-Dist: python-keycloak==5.1.1
Requires-Dist: python-slugify==8.0.1
Requires-Dist: responses==0.25.8
Requires-Dist: sentry-sdk==1.9.0
Summary: Energy Community
Home-page: https://git.coopdevs.org/coopdevs/comunitats-energetiques/odoo-ce
License: AGPL-3
Author: Coopdevs Treball SCCL & Som Energia SCCL
Classifier: Programming Language :: Python
Classifier: Framework :: Odoo
Classifier: Framework :: Odoo :: 16.0
Classifier: License :: OSI Approved :: GNU Affero General Public License v3
